img_encrypt/__init__.py
img_encrypt-0.1.1.dist-info/LICENSE.txt
img_encrypt-0.1.1.dist-info/METADATA
img_encrypt-0.1.1.dist-info/WHEEL
img_encrypt-0.1.1.dist-info/top_level.txt
img_encrypt-0.1.1.dist-info/RECORD
