Metadata-Version: 2.1
Name: img-encrypt
Version: 0.1.1
Summary: One Converter for Encrypt and Decrypt.
Home-page: https://github.com/mr-ahir-is-here
Author: Amit
Author-email: haddbtc@gmail.com
License: UNKNOWN
Platform: UNKNOWN
Classifier: Programming Language :: Python :: 3
Classifier: License :: OSI Approved :: MIT License
Classifier: Operating System :: OS Independent
Requires-Python: >=3.6
